notemind/__init__.py
notemind/xmind/__init__.py
notemind/xmind/utils.py
notemind/xmind/core/__init__.py
notemind/xmind/core/comments.py
notemind/xmind/core/const.py
notemind/xmind/core/labels.py
notemind/xmind/core/loader.py
notemind/xmind/core/markerref.py
notemind/xmind/core/mixin.py
notemind/xmind/core/notes.py
notemind/xmind/core/position.py
notemind/xmind/core/relationship.py
notemind/xmind/core/saver.py
notemind/xmind/core/sheet.py
notemind/xmind/core/styles.py
notemind/xmind/core/title.py
notemind/xmind/core/topic.py
notemind/xmind/core/workbook.py
notemind-0.0.2.dist-info/METADATA
notemind-0.0.2.dist-info/WHEEL
notemind-0.0.2.dist-info/top_level.txt
notemind-0.0.2.dist-info/RECORD
